asciiWriter/__init__.py
asciiWriter/asciiWriter.py
asciiWriter/marks.py
asciiWriter/patterns.py
asciiWriter/text.py
asciiWriter/utils.py
asciiWriter/wrap_single_line.py
asciiWriter/examples/draw.py
asciiWriter/examples/image.py
asciiWriter/examples/image_random_char.py
asciiWriter/examples/image_rotate.py
asciiWriter/examples/image_sentence.py
asciiWriter/examples/line.py
asciiWriter/examples/line_random_char.py
asciiWriter/examples/multi_column_page.py
asciiWriter/examples/repeated_line.py
asciiWriter/examples/repeated_sinus.py
asciiWriter/examples/repeated_sinus_amplitude_variation.py
asciiWriter/examples/single_column_page.py
asciiWriter/examples/sinus.py
asciiWriter/examples/test.py
asciiWriter/examples/data/blobs-small.png
asciiWriter/examples/data/blobs.png
asciiWriter/examples/data/language.txt
asciiWriter/examples/data/shapes.png
asciiWriter-0.0.3.dist-info/LICENSE.txt
asciiWriter-0.0.3.dist-info/METADATA
asciiWriter-0.0.3.dist-info/WHEEL
asciiWriter-0.0.3.dist-info/top_level.txt
asciiWriter-0.0.3.dist-info/RECORD
