Metadata-Version: 2.1
Name: asciiWriter
Version: 0.0.3
Summary: A python library to draw with ASCII (but with Unicode)
Home-page: https://git.vvvvvvaria.org/mb/asciiWriter
Author: Gijs de Heij, Manetta Berends
Author-email: asciiwriter@osp.kitchen, info@varia.zone
License: LICENSE.txt
Keywords: plaintext,layout software,ascii art
Platform: UNKNOWN
